bq_meta/__init__.py
bq_meta/__main__.py
bq_meta/auth.py
bq_meta/cli.py
bq_meta/client.py
bq_meta/config.py
bq_meta/const.py
bq_meta/initialize.py
bq_meta/output.py
bq_meta/window.py
bq_meta/service/__init__.py
bq_meta/service/history_service.py
bq_meta/service/iam_service.py
bq_meta/service/project_service.py
bq_meta/service/snippet_service.py
bq_meta/service/table_service.py
bq_meta/service/version_service.py
bq_meta/snippets/dataset_size
bq_meta/snippets/duplicate_count
bq_meta/snippets/duplicate_rows
bq_meta/snippets/month_size
bq_meta/snippets/partition_size
bq_meta/snippets/table_ddl
bq_meta/util/__init__.py
bq_meta/util/bash_util.py
bq_meta/util/num_utils.py
bq_meta/util/rich_utils.py
bq_meta/util/table_utils.py
bq_meta-0.9.0.dist-info/LICENSE
bq_meta-0.9.0.dist-info/METADATA
bq_meta-0.9.0.dist-info/WHEEL
bq_meta-0.9.0.dist-info/entry_points.txt
bq_meta-0.9.0.dist-info/top_level.txt
bq_meta-0.9.0.dist-info/RECORD
