Metadata-Version: 2.1
Name: bq-meta
Version: 0.9.0
Summary: BigQuery metadata
Home-page: https://github.com/martintupy/bq-meta
Author: Martin Tupy
Author-email: id@martintupy.com
License: Apache-2.0
Classifier: License :: OSI Approved :: Apache Software License
Classifier: Programming Language :: Python :: 3
Classifier: Programming Language :: Python :: 3 :: Only
Classifier: Programming Language :: Python :: 3.10
Classifier: Programming Language :: Python :: 3.11
Requires-Python: >=3.10
License-File: LICENSE
Requires-Dist: Click
Requires-Dist: google-cloud-asset
Requires-Dist: google-auth-oauthlib
Requires-Dist: google-cloud-bigquery
Requires-Dist: google-api-python-client
Requires-Dist: jinja2
Requires-Dist: pyperclip
Requires-Dist: pyyaml
Requires-Dist: readchar
Requires-Dist: rich
Requires-Dist: loguru
